{
  "activity_id": "LEA-EY-ACT-0132",
  "title": "Fluency: Accuracy, Rate And Phrasing - Find the Mistake 4",
  "grade_band": "Grade 2",
  "mechanic": "Find the Mistake",
  "learning_goal": "Learner can accuracy, rate and phrasing through a short guided find the mistake activity.",
  "mastery_rule": "Mastered at accuracy >= 0.85, prompt_level <= 2, across 2 completed sessions",
  "remediation_trigger": "Route to targeted mini-teach if accuracy < 0.70 after 5 items, consecutive_same_error_count >= 2, or response_time_seconds > baseline_average_response_time_seconds * 1.50 and accuracy == 1.0",
  "extension_unlock": "Unlock challenge when accuracy >= 0.90, prompt_level <= 1, and response_time_seconds <= baseline_average_response_time_seconds * 1.10",
  "items": [
    {
      "item_id": "LEA-EY-ACT-0132-ITEM-01",
      "activity_id": "LEA-EY-ACT-0132",
      "activity_version": "1.2",
      "grade_band": "Grade 2",
      "strand": "Fluency",
      "skill_code": "EY-GRA-LIT-FLU-04",
      "mechanic": "Find the Mistake",
      "prompt_text": "Find the correct sentence. The mistake sentence is: 'The record are clear.'",
      "prompt_audio_text": "Find the mistake and choose the correction. Find the correct sentence. The mistake sentence is: 'The record are clear.'",
      "answer_format": "text",
      "item_type": "single_choice",
      "correct_answer": "The record is clear.",
      "distractors": [
        "The record clear is.",
        "The record are clear.",
        "Clear the record is."
      ],
      "choices": [
        "The record clear is.",
        "The record are clear.",
        "Clear the record is.",
        "The record is clear."
      ],
      "feedback": {
        "correct": "Excellent. You are ready for the next item.",
        "incorrect": "Try again. Listen once more, use the hint, and choose carefully.",
        "hint": "Look for the clue linked to accuracy, rate and phrasing.",
        "interventions_by_error_type": {
          "grammar_agreement": "Mini-teach: model one example of accuracy, rate and phrasing, practise one guided item, then return to the task.",
          "slow_correct": "Praise accuracy, remove time pressure, and build fluency with two repeated examples.",
          "multiple_attempts": "Reduce choices to two and replay the audio prompt."
        }
      },
      "assets": {
        "illustrated_card_svg": "/media/cards/svg/LEA-EY-ACT-0132-ITEM-01-CARD.svg",
        "success_animation": "/media/animations/lottie/success_star.json",
        "audio_ssml": "/media/audio/ssml/LEA-EY-ACT-0132-ITEM-01.ssml",
        "audio_target_url": "/media/audio/mp3/LEA-EY-ACT-0132-ITEM-01.mp3"
      },
      "telemetry_expected": [
        "accuracy",
        "prompt_level",
        "response_time_seconds",
        "attempt_count",
        "error_type",
        "hint_count",
        "audio_replay_count"
      ],
      "accessibility": {
        "alt_text": "Illustrated card for The record is clear.",
        "caption_text": "Find the correct sentence. The mistake sentence is: 'The record are clear.'",
        "keyboard_focus_order": 1
      }
    },
    {
      "item_id": "LEA-EY-ACT-0132-ITEM-02",
      "activity_id": "LEA-EY-ACT-0132",
      "activity_version": "1.2",
      "grade_band": "Grade 2",
      "strand": "Fluency",
      "skill_code": "EY-GRA-LIT-FLU-04",
      "mechanic": "Find the Mistake",
      "prompt_text": "Find the correct sentence. The mistake sentence is: 'The sentence are clear.'",
      "prompt_audio_text": "Find the mistake and choose the correction. Find the correct sentence. The mistake sentence is: 'The sentence are clear.'",
      "answer_format": "text",
      "item_type": "single_choice",
      "correct_answer": "The sentence is clear.",
      "distractors": [
        "The sentence are clear.",
        "Clear the sentence is.",
        "The sentence clear is."
      ],
      "choices": [
        "The sentence is clear.",
        "The sentence are clear.",
        "Clear the sentence is.",
        "The sentence clear is."
      ],
      "feedback": {
        "correct": "Great work. You listened carefully.",
        "incorrect": "Try again. Listen once more, use the hint, and choose carefully.",
        "hint": "Look for the clue linked to accuracy, rate and phrasing.",
        "interventions_by_error_type": {
          "grammar_agreement": "Mini-teach: model one example of accuracy, rate and phrasing, practise one guided item, then return to the task.",
          "slow_correct": "Praise accuracy, remove time pressure, and build fluency with two repeated examples.",
          "multiple_attempts": "Reduce choices to two and replay the audio prompt."
        }
      },
      "assets": {
        "illustrated_card_svg": "/media/cards/svg/LEA-EY-ACT-0132-ITEM-02-CARD.svg",
        "success_animation": "/media/animations/lottie/success_star.json",
        "audio_ssml": "/media/audio/ssml/LEA-EY-ACT-0132-ITEM-02.ssml",
        "audio_target_url": "/media/audio/mp3/LEA-EY-ACT-0132-ITEM-02.mp3"
      },
      "telemetry_expected": [
        "accuracy",
        "prompt_level",
        "response_time_seconds",
        "attempt_count",
        "error_type",
        "hint_count",
        "audio_replay_count"
      ],
      "accessibility": {
        "alt_text": "Illustrated card for The sentence is clear.",
        "caption_text": "Find the correct sentence. The mistake sentence is: 'The sentence are clear.'",
        "keyboard_focus_order": 2
      }
    },
    {
      "item_id": "LEA-EY-ACT-0132-ITEM-03",
      "activity_id": "LEA-EY-ACT-0132",
      "activity_version": "1.2",
      "grade_band": "Grade 2",
      "strand": "Fluency",
      "skill_code": "EY-GRA-LIT-FLU-04",
      "mechanic": "Find the Mistake",
      "prompt_text": "Find the correct sentence. The mistake sentence is: 'The paragraph are clear.'",
      "prompt_audio_text": "Find the mistake and choose the correction. Find the correct sentence. The mistake sentence is: 'The paragraph are clear.'",
      "answer_format": "text",
      "item_type": "single_choice",
      "correct_answer": "The paragraph is clear.",
      "distractors": [
        "Clear the paragraph is.",
        "The paragraph clear is.",
        "The paragraph are clear."
      ],
      "choices": [
        "Clear the paragraph is.",
        "The paragraph clear is.",
        "The paragraph are clear.",
        "The paragraph is clear."
      ],
      "feedback": {
        "correct": "Great work. You listened carefully.",
        "incorrect": "Try again. Listen once more, use the hint, and choose carefully.",
        "hint": "Look for the clue linked to accuracy, rate and phrasing.",
        "interventions_by_error_type": {
          "grammar_agreement": "Mini-teach: model one example of accuracy, rate and phrasing, practise one guided item, then return to the task.",
          "slow_correct": "Praise accuracy, remove time pressure, and build fluency with two repeated examples.",
          "multiple_attempts": "Reduce choices to two and replay the audio prompt."
        }
      },
      "assets": {
        "illustrated_card_svg": "/media/cards/svg/LEA-EY-ACT-0132-ITEM-03-CARD.svg",
        "success_animation": "/media/animations/lottie/success_star.json",
        "audio_ssml": "/media/audio/ssml/LEA-EY-ACT-0132-ITEM-03.ssml",
        "audio_target_url": "/media/audio/mp3/LEA-EY-ACT-0132-ITEM-03.mp3"
      },
      "telemetry_expected": [
        "accuracy",
        "prompt_level",
        "response_time_seconds",
        "attempt_count",
        "error_type",
        "hint_count",
        "audio_replay_count"
      ],
      "accessibility": {
        "alt_text": "Illustrated card for The paragraph is clear.",
        "caption_text": "Find the correct sentence. The mistake sentence is: 'The paragraph are clear.'",
        "keyboard_focus_order": 3
      }
    },
    {
      "item_id": "LEA-EY-ACT-0132-ITEM-04",
      "activity_id": "LEA-EY-ACT-0132",
      "activity_version": "1.2",
      "grade_band": "Grade 2",
      "strand": "Fluency",
      "skill_code": "EY-GRA-LIT-FLU-04",
      "mechanic": "Find the Mistake",
      "prompt_text": "Find the correct sentence. The mistake sentence is: 'The topic are clear.'",
      "prompt_audio_text": "Find the mistake and choose the correction. Find the correct sentence. The mistake sentence is: 'The topic are clear.'",
      "answer_format": "text",
      "item_type": "single_choice",
      "correct_answer": "The topic is clear.",
      "distractors": [
        "The topic are clear.",
        "The topic clear is.",
        "Clear the topic is."
      ],
      "choices": [
        "The topic are clear.",
        "The topic is clear.",
        "The topic clear is.",
        "Clear the topic is."
      ],
      "feedback": {
        "correct": "Well done. You chose the best answer.",
        "incorrect": "Try again. Listen once more, use the hint, and choose carefully.",
        "hint": "Look for the clue linked to accuracy, rate and phrasing.",
        "interventions_by_error_type": {
          "grammar_agreement": "Mini-teach: model one example of accuracy, rate and phrasing, practise one guided item, then return to the task.",
          "slow_correct": "Praise accuracy, remove time pressure, and build fluency with two repeated examples.",
          "multiple_attempts": "Reduce choices to two and replay the audio prompt."
        }
      },
      "assets": {
        "illustrated_card_svg": "/media/cards/svg/LEA-EY-ACT-0132-ITEM-04-CARD.svg",
        "success_animation": "/media/animations/lottie/success_star.json",
        "audio_ssml": "/media/audio/ssml/LEA-EY-ACT-0132-ITEM-04.ssml",
        "audio_target_url": "/media/audio/mp3/LEA-EY-ACT-0132-ITEM-04.mp3"
      },
      "telemetry_expected": [
        "accuracy",
        "prompt_level",
        "response_time_seconds",
        "attempt_count",
        "error_type",
        "hint_count",
        "audio_replay_count"
      ],
      "accessibility": {
        "alt_text": "Illustrated card for The topic is clear.",
        "caption_text": "Find the correct sentence. The mistake sentence is: 'The topic are clear.'",
        "keyboard_focus_order": 4
      }
    },
    {
      "item_id": "LEA-EY-ACT-0132-ITEM-05",
      "activity_id": "LEA-EY-ACT-0132",
      "activity_version": "1.2",
      "grade_band": "Grade 2",
      "strand": "Fluency",
      "skill_code": "EY-GRA-LIT-FLU-04",
      "mechanic": "Find the Mistake",
      "prompt_text": "Find the correct sentence. The mistake sentence is: 'The detail are clear.'",
      "prompt_audio_text": "Find the mistake and choose the correction. Find the correct sentence. The mistake sentence is: 'The detail are clear.'",
      "answer_format": "text",
      "item_type": "single_choice",
      "correct_answer": "The detail is clear.",
      "distractors": [
        "The detail are clear.",
        "The detail clear is.",
        "Clear the detail is."
      ],
      "choices": [
        "The detail are clear.",
        "The detail is clear.",
        "The detail clear is.",
        "Clear the detail is."
      ],
      "feedback": {
        "correct": "Great work. You listened carefully.",
        "incorrect": "Try again. Listen once more, use the hint, and choose carefully.",
        "hint": "Look for the clue linked to accuracy, rate and phrasing.",
        "interventions_by_error_type": {
          "grammar_agreement": "Mini-teach: model one example of accuracy, rate and phrasing, practise one guided item, then return to the task.",
          "slow_correct": "Praise accuracy, remove time pressure, and build fluency with two repeated examples.",
          "multiple_attempts": "Reduce choices to two and replay the audio prompt."
        }
      },
      "assets": {
        "illustrated_card_svg": "/media/cards/svg/LEA-EY-ACT-0132-ITEM-05-CARD.svg",
        "success_animation": "/media/animations/lottie/success_star.json",
        "audio_ssml": "/media/audio/ssml/LEA-EY-ACT-0132-ITEM-05.ssml",
        "audio_target_url": "/media/audio/mp3/LEA-EY-ACT-0132-ITEM-05.mp3"
      },
      "telemetry_expected": [
        "accuracy",
        "prompt_level",
        "response_time_seconds",
        "attempt_count",
        "error_type",
        "hint_count",
        "audio_replay_count"
      ],
      "accessibility": {
        "alt_text": "Illustrated card for The detail is clear.",
        "caption_text": "Find the correct sentence. The mistake sentence is: 'The detail are clear.'",
        "keyboard_focus_order": 5
      }
    },
    {
      "item_id": "LEA-EY-ACT-0132-ITEM-06",
      "activity_id": "LEA-EY-ACT-0132",
      "activity_version": "1.2",
      "grade_band": "Grade 2",
      "strand": "Fluency",
      "skill_code": "EY-GRA-LIT-FLU-04",
      "mechanic": "Find the Mistake",
      "prompt_text": "Find the correct sentence. The mistake sentence is: 'The reason are clear.'",
      "prompt_audio_text": "Find the mistake and choose the correction. Find the correct sentence. The mistake sentence is: 'The reason are clear.'",
      "answer_format": "text",
      "item_type": "single_choice",
      "correct_answer": "The reason is clear.",
      "distractors": [
        "Clear the reason is.",
        "The reason clear is.",
        "The reason are clear."
      ],
      "choices": [
        "The reason is clear.",
        "Clear the reason is.",
        "The reason clear is.",
        "The reason are clear."
      ],
      "feedback": {
        "correct": "Excellent. You are ready for the next item.",
        "incorrect": "Try again. Listen once more, use the hint, and choose carefully.",
        "hint": "Look for the clue linked to accuracy, rate and phrasing.",
        "interventions_by_error_type": {
          "grammar_agreement": "Mini-teach: model one example of accuracy, rate and phrasing, practise one guided item, then return to the task.",
          "slow_correct": "Praise accuracy, remove time pressure, and build fluency with two repeated examples.",
          "multiple_attempts": "Reduce choices to two and replay the audio prompt."
        }
      },
      "assets": {
        "illustrated_card_svg": "/media/cards/svg/LEA-EY-ACT-0132-ITEM-06-CARD.svg",
        "success_animation": "/media/animations/lottie/success_star.json",
        "audio_ssml": "/media/audio/ssml/LEA-EY-ACT-0132-ITEM-06.ssml",
        "audio_target_url": "/media/audio/mp3/LEA-EY-ACT-0132-ITEM-06.mp3"
      },
      "telemetry_expected": [
        "accuracy",
        "prompt_level",
        "response_time_seconds",
        "attempt_count",
        "error_type",
        "hint_count",
        "audio_replay_count"
      ],
      "accessibility": {
        "alt_text": "Illustrated card for The reason is clear.",
        "caption_text": "Find the correct sentence. The mistake sentence is: 'The reason are clear.'",
        "keyboard_focus_order": 6
      }
    },
    {
      "item_id": "LEA-EY-ACT-0132-ITEM-07",
      "activity_id": "LEA-EY-ACT-0132",
      "activity_version": "1.2",
      "grade_band": "Grade 2",
      "strand": "Fluency",
      "skill_code": "EY-GRA-LIT-FLU-04",
      "mechanic": "Find the Mistake",
      "prompt_text": "Find the correct sentence. The mistake sentence is: 'The example are clear.'",
      "prompt_audio_text": "Find the mistake and choose the correction. Find the correct sentence. The mistake sentence is: 'The example are clear.'",
      "answer_format": "text",
      "item_type": "single_choice",
      "correct_answer": "The example is clear.",
      "distractors": [
        "The example are clear.",
        "The example clear is.",
        "Clear the example is."
      ],
      "choices": [
        "The example are clear.",
        "The example clear is.",
        "Clear the example is.",
        "The example is clear."
      ],
      "feedback": {
        "correct": "Excellent. You are ready for the next item.",
        "incorrect": "Try again. Listen once more, use the hint, and choose carefully.",
        "hint": "Look for the clue linked to accuracy, rate and phrasing.",
        "interventions_by_error_type": {
          "grammar_agreement": "Mini-teach: model one example of accuracy, rate and phrasing, practise one guided item, then return to the task.",
          "slow_correct": "Praise accuracy, remove time pressure, and build fluency with two repeated examples.",
          "multiple_attempts": "Reduce choices to two and replay the audio prompt."
        }
      },
      "assets": {
        "illustrated_card_svg": "/media/cards/svg/LEA-EY-ACT-0132-ITEM-07-CARD.svg",
        "success_animation": "/media/animations/lottie/success_star.json",
        "audio_ssml": "/media/audio/ssml/LEA-EY-ACT-0132-ITEM-07.ssml",
        "audio_target_url": "/media/audio/mp3/LEA-EY-ACT-0132-ITEM-07.mp3"
      },
      "telemetry_expected": [
        "accuracy",
        "prompt_level",
        "response_time_seconds",
        "attempt_count",
        "error_type",
        "hint_count",
        "audio_replay_count"
      ],
      "accessibility": {
        "alt_text": "Illustrated card for The example is clear.",
        "caption_text": "Find the correct sentence. The mistake sentence is: 'The example are clear.'",
        "keyboard_focus_order": 7
      }
    },
    {
      "item_id": "LEA-EY-ACT-0132-ITEM-08",
      "activity_id": "LEA-EY-ACT-0132",
      "activity_version": "1.2",
      "grade_band": "Grade 2",
      "strand": "Fluency",
      "skill_code": "EY-GRA-LIT-FLU-04",
      "mechanic": "Find the Mistake",
      "prompt_text": "Find the correct sentence. The mistake sentence is: 'The compare are clear.'",
      "prompt_audio_text": "Find the mistake and choose the correction. Find the correct sentence. The mistake sentence is: 'The compare are clear.'",
      "answer_format": "text",
      "item_type": "single_choice",
      "correct_answer": "The compare is clear.",
      "distractors": [
        "Clear the compare is.",
        "The compare are clear.",
        "The compare clear is."
      ],
      "choices": [
        "The compare is clear.",
        "Clear the compare is.",
        "The compare are clear.",
        "The compare clear is."
      ],
      "feedback": {
        "correct": "Well done. You chose the best answer.",
        "incorrect": "Try again. Listen once more, use the hint, and choose carefully.",
        "hint": "Look for the clue linked to accuracy, rate and phrasing.",
        "interventions_by_error_type": {
          "grammar_agreement": "Mini-teach: model one example of accuracy, rate and phrasing, practise one guided item, then return to the task.",
          "slow_correct": "Praise accuracy, remove time pressure, and build fluency with two repeated examples.",
          "multiple_attempts": "Reduce choices to two and replay the audio prompt."
        }
      },
      "assets": {
        "illustrated_card_svg": "/media/cards/svg/LEA-EY-ACT-0132-ITEM-08-CARD.svg",
        "success_animation": "/media/animations/lottie/success_star.json",
        "audio_ssml": "/media/audio/ssml/LEA-EY-ACT-0132-ITEM-08.ssml",
        "audio_target_url": "/media/audio/mp3/LEA-EY-ACT-0132-ITEM-08.mp3"
      },
      "telemetry_expected": [
        "accuracy",
        "prompt_level",
        "response_time_seconds",
        "attempt_count",
        "error_type",
        "hint_count",
        "audio_replay_count"
      ],
      "accessibility": {
        "alt_text": "Illustrated card for The compare is clear.",
        "caption_text": "Find the correct sentence. The mistake sentence is: 'The compare are clear.'",
        "keyboard_focus_order": 8
      }
    },
    {
      "item_id": "LEA-EY-ACT-0132-ITEM-09",
      "activity_id": "LEA-EY-ACT-0132",
      "activity_version": "1.2",
      "grade_band": "Grade 2",
      "strand": "Fluency",
      "skill_code": "EY-GRA-LIT-FLU-04",
      "mechanic": "Find the Mistake",
      "prompt_text": "Find the correct sentence. The mistake sentence is: 'The explain are clear.'",
      "prompt_audio_text": "Find the mistake and choose the correction. Find the correct sentence. The mistake sentence is: 'The explain are clear.'",
      "answer_format": "text",
      "item_type": "single_choice",
      "correct_answer": "The explain is clear.",
      "distractors": [
        "The explain clear is.",
        "Clear the explain is.",
        "The explain are clear."
      ],
      "choices": [
        "The explain clear is.",
        "Clear the explain is.",
        "The explain is clear.",
        "The explain are clear."
      ],
      "feedback": {
        "correct": "Excellent. You are ready for the next item.",
        "incorrect": "Try again. Listen once more, use the hint, and choose carefully.",
        "hint": "Look for the clue linked to accuracy, rate and phrasing.",
        "interventions_by_error_type": {
          "grammar_agreement": "Mini-teach: model one example of accuracy, rate and phrasing, practise one guided item, then return to the task.",
          "slow_correct": "Praise accuracy, remove time pressure, and build fluency with two repeated examples.",
          "multiple_attempts": "Reduce choices to two and replay the audio prompt."
        }
      },
      "assets": {
        "illustrated_card_svg": "/media/cards/svg/LEA-EY-ACT-0132-ITEM-09-CARD.svg",
        "success_animation": "/media/animations/lottie/success_star.json",
        "audio_ssml": "/media/audio/ssml/LEA-EY-ACT-0132-ITEM-09.ssml",
        "audio_target_url": "/media/audio/mp3/LEA-EY-ACT-0132-ITEM-09.mp3"
      },
      "telemetry_expected": [
        "accuracy",
        "prompt_level",
        "response_time_seconds",
        "attempt_count",
        "error_type",
        "hint_count",
        "audio_replay_count"
      ],
      "accessibility": {
        "alt_text": "Illustrated card for The explain is clear.",
        "caption_text": "Find the correct sentence. The mistake sentence is: 'The explain are clear.'",
        "keyboard_focus_order": 9
      }
    },
    {
      "item_id": "LEA-EY-ACT-0132-ITEM-10",
      "activity_id": "LEA-EY-ACT-0132",
      "activity_version": "1.2",
      "grade_band": "Grade 2",
      "strand": "Fluency",
      "skill_code": "EY-GRA-LIT-FLU-04",
      "mechanic": "Find the Mistake",
      "prompt_text": "Find the correct sentence. The mistake sentence is: 'The describe are clear.'",
      "prompt_audio_text": "Find the mistake and choose the correction. Find the correct sentence. The mistake sentence is: 'The describe are clear.'",
      "answer_format": "text",
      "item_type": "single_choice",
      "correct_answer": "The describe is clear.",
      "distractors": [
        "Clear the describe is.",
        "The describe are clear.",
        "The describe clear is."
      ],
      "choices": [
        "The describe is clear.",
        "Clear the describe is.",
        "The describe are clear.",
        "The describe clear is."
      ],
      "feedback": {
        "correct": "Great work. You listened carefully.",
        "incorrect": "Try again. Listen once more, use the hint, and choose carefully.",
        "hint": "Look for the clue linked to accuracy, rate and phrasing.",
        "interventions_by_error_type": {
          "grammar_agreement": "Mini-teach: model one example of accuracy, rate and phrasing, practise one guided item, then return to the task.",
          "slow_correct": "Praise accuracy, remove time pressure, and build fluency with two repeated examples.",
          "multiple_attempts": "Reduce choices to two and replay the audio prompt."
        }
      },
      "assets": {
        "illustrated_card_svg": "/media/cards/svg/LEA-EY-ACT-0132-ITEM-10-CARD.svg",
        "success_animation": "/media/animations/lottie/success_star.json",
        "audio_ssml": "/media/audio/ssml/LEA-EY-ACT-0132-ITEM-10.ssml",
        "audio_target_url": "/media/audio/mp3/LEA-EY-ACT-0132-ITEM-10.mp3"
      },
      "telemetry_expected": [
        "accuracy",
        "prompt_level",
        "response_time_seconds",
        "attempt_count",
        "error_type",
        "hint_count",
        "audio_replay_count"
      ],
      "accessibility": {
        "alt_text": "Illustrated card for The describe is clear.",
        "caption_text": "Find the correct sentence. The mistake sentence is: 'The describe are clear.'",
        "keyboard_focus_order": 10
      }
    }
  ]
}